[
  {
    "detail" : "박세한-이다솜(언어) 3\/27 보강",
    "detailH" : 36,
    "detailW" : 25,
    "detailX" : 1335,
    "detailY" : 615,
    "pass" : 0,
    "screenshot" : "output\/status_probe_2026_04\/2026_04_04_pass0.png",
    "time" : "9:00",
    "timeH" : 36,
    "timeW" : 62,
    "timeX" : 1274,
    "timeY" : 615
  },
  {
    "detail" : "천서현-김상희(놀이)",
    "detailH" : 36,
    "detailW" : 25,
    "detailX" : 1335,
    "detailY" : 651,
    "pass" : 0,
    "screenshot" : "output\/status_probe_2026_04\/2026_04_04_pass0.png",
    "time" : "9:30",
    "timeH" : 36,
    "timeW" : 62,
    "timeX" : 1274,
    "timeY" : 651
  },
  {
    "detail" : "장아윤-이다솜(언어)",
    "detailH" : 37,
    "detailW" : 25,
    "detailX" : 1335,
    "detailY" : 686,
    "pass" : 0,
    "screenshot" : "output\/status_probe_2026_04\/2026_04_04_pass0.png",
    "time" : "9:45",
    "timeH" : 37,
    "timeW" : 62,
    "timeX" : 1274,
    "timeY" : 686
  },
  {
    "detail" : "장아윤-김상희(놀이)",
    "detailH" : 36,
    "detailW" : 25,
    "detailX" : 1335,
    "detailY" : 722,
    "pass" : 0,
    "screenshot" : "output\/status_probe_2026_04\/2026_04_04_pass0.png",
    "time" : "10:30",
    "timeH" : 36,
    "timeW" : 62,
    "timeX" : 1274,
    "timeY" : 722
  },
  {
    "detail" : "이서준-이다솜(언어) 언어평가 결과상담",
    "detailH" : 36,
    "detailW" : 25,
    "detailX" : 1335,
    "detailY" : 758,
    "pass" : 0,
    "screenshot" : "output\/status_probe_2026_04\/2026_04_04_pass0.png",
    "time" : "11:00",
    "timeH" : 36,
    "timeW" : 62,
    "timeX" : 1274,
    "timeY" : 758
  },
  {
    "detail" : "김도윤-김상희(놀이)",
    "detailH" : 36,
    "detailW" : 25,
    "detailX" : 1335,
    "detailY" : 793,
    "pass" : 0,
    "screenshot" : "output\/status_probe_2026_04\/2026_04_04_pass0.png",
    "time" : "11:15",
    "timeH" : 36,
    "timeW" : 62,
    "timeX" : 1274,
    "timeY" : 793
  },
  {
    "detail" : "이서진-이다솜(언어) 일정변경\/ 보강 조율 필요",
    "detailH" : 36,
    "detailW" : 25,
    "detailX" : 1335,
    "detailY" : 829,
    "pass" : 0,
    "screenshot" : "output\/status_probe_2026_04\/2026_04_04_pass0.png",
    "time" : "11:15",
    "timeH" : 36,
    "timeW" : 62,
    "timeX" : 1274,
    "timeY" : 829
  },
  {
    "detail" : "이소영-김상희(놀이)",
    "detailH" : 36,
    "detailW" : 25,
    "detailX" : 1335,
    "detailY" : 864,
    "pass" : 0,
    "screenshot" : "output\/status_probe_2026_04\/2026_04_04_pass0.png",
    "time" : "12:00",
    "timeH" : 36,
    "timeW" : 62,
    "timeX" : 1274,
    "timeY" : 864
  },
  {
    "detail" : "홍사랑-김상희(놀이)",
    "detailH" : 36,
    "detailW" : 25,
    "detailX" : 1335,
    "detailY" : 900,
    "pass" : 0,
    "screenshot" : "output\/status_probe_2026_04\/2026_04_04_pass0.png",
    "time" : "12:40",
    "timeH" : 36,
    "timeW" : 62,
    "timeX" : 1274,
    "timeY" : 900
  },
  {
    "detail" : "이연두-김상희(놀이)",
    "detailH" : 36,
    "detailW" : 25,
    "detailX" : 1335,
    "detailY" : 935,
    "pass" : 0,
    "screenshot" : "output\/status_probe_2026_04\/2026_04_04_pass0.png",
    "time" : "13:30",
    "timeH" : 36,
    "timeW" : 62,
    "timeX" : 1274,
    "timeY" : 935
  },
  {
    "detail" : "박세한-이다솜(언어) 3\/27 보강",
    "detailH" : 36,
    "detailW" : 25,
    "detailX" : 1335,
    "detailY" : -156,
    "pass" : 1,
    "screenshot" : "output\/status_probe_2026_04\/2026_04_04_pass1.png",
    "time" : "9:00",
    "timeH" : 36,
    "timeW" : 62,
    "timeX" : 1274,
    "timeY" : -156
  },
  {
    "detail" : "천서현-김상희(놀이)",
    "detailH" : 36,
    "detailW" : 25,
    "detailX" : 1335,
    "detailY" : -121,
    "pass" : 1,
    "screenshot" : "output\/status_probe_2026_04\/2026_04_04_pass1.png",
    "time" : "9:30",
    "timeH" : 36,
    "timeW" : 62,
    "timeX" : 1274,
    "timeY" : -121
  },
  {
    "detail" : "장아윤-이다솜(언어)",
    "detailH" : 36,
    "detailW" : 25,
    "detailX" : 1335,
    "detailY" : -85,
    "pass" : 1,
    "screenshot" : "output\/status_probe_2026_04\/2026_04_04_pass1.png",
    "time" : "9:45",
    "timeH" : 36,
    "timeW" : 62,
    "timeX" : 1274,
    "timeY" : -85
  },
  {
    "detail" : "장아윤-김상희(놀이)",
    "detailH" : 36,
    "detailW" : 25,
    "detailX" : 1335,
    "detailY" : -49,
    "pass" : 1,
    "screenshot" : "output\/status_probe_2026_04\/2026_04_04_pass1.png",
    "time" : "10:30",
    "timeH" : 36,
    "timeW" : 62,
    "timeX" : 1274,
    "timeY" : -49
  },
  {
    "detail" : "이서준-이다솜(언어) 언어평가 결과상담",
    "detailH" : 37,
    "detailW" : 25,
    "detailX" : 1335,
    "detailY" : -14,
    "pass" : 1,
    "screenshot" : "output\/status_probe_2026_04\/2026_04_04_pass1.png",
    "time" : "11:00",
    "timeH" : 37,
    "timeW" : 62,
    "timeX" : 1274,
    "timeY" : -14
  },
  {
    "detail" : "김도윤-김상희(놀이)",
    "detailH" : 36,
    "detailW" : 25,
    "detailX" : 1335,
    "detailY" : 22,
    "pass" : 1,
    "screenshot" : "output\/status_probe_2026_04\/2026_04_04_pass1.png",
    "time" : "11:15",
    "timeH" : 36,
    "timeW" : 62,
    "timeX" : 1274,
    "timeY" : 22
  },
  {
    "detail" : "이서진-이다솜(언어) 일정변경\/ 보강 조율 필요",
    "detailH" : 36,
    "detailW" : 25,
    "detailX" : 1335,
    "detailY" : 58,
    "pass" : 1,
    "screenshot" : "output\/status_probe_2026_04\/2026_04_04_pass1.png",
    "time" : "11:15",
    "timeH" : 36,
    "timeW" : 62,
    "timeX" : 1274,
    "timeY" : 58
  },
  {
    "detail" : "이소영-김상희(놀이)",
    "detailH" : 36,
    "detailW" : 25,
    "detailX" : 1335,
    "detailY" : 93,
    "pass" : 1,
    "screenshot" : "output\/status_probe_2026_04\/2026_04_04_pass1.png",
    "time" : "12:00",
    "timeH" : 36,
    "timeW" : 62,
    "timeX" : 1274,
    "timeY" : 93
  },
  {
    "detail" : "홍사랑-김상희(놀이)",
    "detailH" : 36,
    "detailW" : 25,
    "detailX" : 1335,
    "detailY" : 129,
    "pass" : 1,
    "screenshot" : "output\/status_probe_2026_04\/2026_04_04_pass1.png",
    "time" : "12:40",
    "timeH" : 36,
    "timeW" : 62,
    "timeX" : 1274,
    "timeY" : 129
  },
  {
    "detail" : "이연두-김상희(놀이)",
    "detailH" : 36,
    "detailW" : 25,
    "detailX" : 1335,
    "detailY" : 164,
    "pass" : 1,
    "screenshot" : "output\/status_probe_2026_04\/2026_04_04_pass1.png",
    "time" : "13:30",
    "timeH" : 36,
    "timeW" : 62,
    "timeX" : 1274,
    "timeY" : 164
  },
  {
    "detail" : "박세한-이다솜(언어) 3\/27 보강",
    "detailH" : 36,
    "detailW" : 25,
    "detailX" : 1335,
    "detailY" : -156,
    "pass" : 2,
    "screenshot" : "output\/status_probe_2026_04\/2026_04_04_pass2.png",
    "time" : "9:00",
    "timeH" : 36,
    "timeW" : 62,
    "timeX" : 1274,
    "timeY" : -156
  },
  {
    "detail" : "천서현-김상희(놀이)",
    "detailH" : 36,
    "detailW" : 25,
    "detailX" : 1335,
    "detailY" : -121,
    "pass" : 2,
    "screenshot" : "output\/status_probe_2026_04\/2026_04_04_pass2.png",
    "time" : "9:30",
    "timeH" : 36,
    "timeW" : 62,
    "timeX" : 1274,
    "timeY" : -121
  },
  {
    "detail" : "장아윤-이다솜(언어)",
    "detailH" : 36,
    "detailW" : 25,
    "detailX" : 1335,
    "detailY" : -85,
    "pass" : 2,
    "screenshot" : "output\/status_probe_2026_04\/2026_04_04_pass2.png",
    "time" : "9:45",
    "timeH" : 36,
    "timeW" : 62,
    "timeX" : 1274,
    "timeY" : -85
  },
  {
    "detail" : "장아윤-김상희(놀이)",
    "detailH" : 36,
    "detailW" : 25,
    "detailX" : 1335,
    "detailY" : -49,
    "pass" : 2,
    "screenshot" : "output\/status_probe_2026_04\/2026_04_04_pass2.png",
    "time" : "10:30",
    "timeH" : 36,
    "timeW" : 62,
    "timeX" : 1274,
    "timeY" : -49
  },
  {
    "detail" : "이서준-이다솜(언어) 언어평가 결과상담",
    "detailH" : 37,
    "detailW" : 25,
    "detailX" : 1335,
    "detailY" : -14,
    "pass" : 2,
    "screenshot" : "output\/status_probe_2026_04\/2026_04_04_pass2.png",
    "time" : "11:00",
    "timeH" : 37,
    "timeW" : 62,
    "timeX" : 1274,
    "timeY" : -14
  },
  {
    "detail" : "김도윤-김상희(놀이)",
    "detailH" : 36,
    "detailW" : 25,
    "detailX" : 1335,
    "detailY" : 22,
    "pass" : 2,
    "screenshot" : "output\/status_probe_2026_04\/2026_04_04_pass2.png",
    "time" : "11:15",
    "timeH" : 36,
    "timeW" : 62,
    "timeX" : 1274,
    "timeY" : 22
  },
  {
    "detail" : "이서진-이다솜(언어) 일정변경\/ 보강 조율 필요",
    "detailH" : 36,
    "detailW" : 25,
    "detailX" : 1335,
    "detailY" : 58,
    "pass" : 2,
    "screenshot" : "output\/status_probe_2026_04\/2026_04_04_pass2.png",
    "time" : "11:15",
    "timeH" : 36,
    "timeW" : 62,
    "timeX" : 1274,
    "timeY" : 58
  },
  {
    "detail" : "이소영-김상희(놀이)",
    "detailH" : 36,
    "detailW" : 25,
    "detailX" : 1335,
    "detailY" : 93,
    "pass" : 2,
    "screenshot" : "output\/status_probe_2026_04\/2026_04_04_pass2.png",
    "time" : "12:00",
    "timeH" : 36,
    "timeW" : 62,
    "timeX" : 1274,
    "timeY" : 93
  },
  {
    "detail" : "홍사랑-김상희(놀이)",
    "detailH" : 36,
    "detailW" : 25,
    "detailX" : 1335,
    "detailY" : 129,
    "pass" : 2,
    "screenshot" : "output\/status_probe_2026_04\/2026_04_04_pass2.png",
    "time" : "12:40",
    "timeH" : 36,
    "timeW" : 62,
    "timeX" : 1274,
    "timeY" : 129
  },
  {
    "detail" : "이연두-김상희(놀이)",
    "detailH" : 36,
    "detailW" : 25,
    "detailX" : 1335,
    "detailY" : 164,
    "pass" : 2,
    "screenshot" : "output\/status_probe_2026_04\/2026_04_04_pass2.png",
    "time" : "13:30",
    "timeH" : 36,
    "timeW" : 62,
    "timeX" : 1274,
    "timeY" : 164
  }
]